Metadata-Version: 2.1
Name: mailru-im-bot-imato
Version: 0.0.17
Summary: Pure Python interface for Bot API. Bot cookbook for Humans.
Home-page: https://github.com/Imato/bot-python
Author: ICQ LLC (Mail.Ru Group)
Author-email: support@icq.com
License: MIT
Keywords: mailru im bot api
Platform: UNKNOWN
Classifier: Intended Audience :: Developers
Classifier: Topic :: Software Development :: Libraries :: Python Modules
Classifier: Topic :: Communications :: Chat
Classifier: Topic :: Internet
Classifier: Programming Language :: Python :: 2
Classifier: Programming Language :: Python :: 2.7
Classifier: Programming Language :: Python :: 3
Classifier: Programming Language :: Python :: 3.4
Classifier: Programming Language :: Python :: 3.5
Classifier: Programming Language :: Python :: 3.6
Classifier: Operating System :: OS Independent
Requires-Python: >= 2.7, != 3.0.*, != 3.1.*, != 3.2.*, != 3.3.*
Requires-Dist: cached-property (==1.5.2)
Requires-Dist: expiringdict (==1.2.1)
Requires-Dist: monotonic (==1.5)
Requires-Dist: python-baseconv (==1.2.2)
Requires-Dist: requests (==2.25.0)
Requires-Dist: six (==1.15.0)
Requires-Dist: gTTS (==2.2.1)
Requires-Dist: urllib3 (==1.26.2)
Requires-Dist: click (==7.1.2)
Requires-Dist: enum34 (==1.1.6) ; python_version < "3.4"
